hytek/__init__.py
hytek/hy3/__init__.py
hytek/hy3/converters.py
hytek/hy3/enums.py
hytek/hy3/file.py
hytek/hy3/records.py
hytek-0.0.7.dist-info/LICENSE
hytek-0.0.7.dist-info/METADATA
hytek-0.0.7.dist-info/WHEEL
hytek-0.0.7.dist-info/top_level.txt
hytek-0.0.7.dist-info/RECORD
