Metadata-Version: 2.1
Name: hytek
Version: 0.0.7
Summary: A simple tool for parsing and manipulating HyTek files.
Author: plun1331
License: BSD 3-Clause
Project-URL: Homepage, https://github.com/plun1331/HyTek
Project-URL: Source, https://github.com/plun1331/HyTek
Project-URL: Tracker, https://github.com/plun1331/HyTek/issues
Classifier: Development Status :: 3 - Alpha
Classifier: Intended Audience :: Developers
Classifier: License :: OSI Approved :: BSD License
Classifier: Programming Language :: Python :: 3
Classifier: Programming Language :: Python :: 3.12
Classifier: Topic :: Internet
Classifier: Topic :: Software Development :: Libraries
Classifier: Topic :: Software Development :: Libraries :: Python Modules
Classifier: Topic :: Utilities
Classifier: Typing :: Typed
Requires-Python: >=3.12
License-File: LICENSE
